sem_ver/__init__.py
sem_ver/py.typed
sem_ver/semver.py
sem_ver-1.2.0.dist-info/METADATA
sem_ver-1.2.0.dist-info/WHEEL
sem_ver-1.2.0.dist-info/top_level.txt
sem_ver-1.2.0.dist-info/RECORD
