Metadata-Version: 2.1
Name: sem-ver
Version: 1.2.0
Summary: Semantic Version Processor
Home-page: https://github.com/plinss/sem_ver/
Author: Peter Linss
Author-email: pypi@linss.com
License: UNKNOWN
Platform: UNKNOWN
Classifier: Programming Language :: Python :: 3
Classifier: License :: OSI Approved :: MIT License
Classifier: Operating System :: OS Independent
Requires-Python: >=3.6
Provides-Extra: dev
Requires-Dist: mypy ; extra == 'dev'
Requires-Dist: flake8 ; extra == 'dev'
Requires-Dist: flake8-import-order ; extra == 'dev'
Requires-Dist: flake8-annotations ; extra == 'dev'
Requires-Dist: flake8-type-annotations ; extra == 'dev'
Requires-Dist: flake8-docstrings ; extra == 'dev'
Requires-Dist: pep8-naming ; extra == 'dev'
